automation.py
farsightai.py
prompts.py
test.py
farsightai-0.2.8.dist-info/LICENSE
farsightai-0.2.8.dist-info/METADATA
farsightai-0.2.8.dist-info/WHEEL
farsightai-0.2.8.dist-info/top_level.txt
farsightai-0.2.8.dist-info/RECORD
