Metadata-Version: 2.1
Name: farsightai
Version: 0.2.8
Summary: Farsight-ai testing suite
Author: Katie Pelton, Andrei Dumitrescu
Classifier: Programming Language :: Python :: 3
Classifier: License :: OSI Approved :: MIT License
Classifier: Operating System :: OS Independent
Requires-Python: >=3.6
License-File: LICENSE
Requires-Dist: openai
Requires-Dist: pytest
